plotly_football_pitch/__init__.py
plotly_football_pitch/pitch_background.py
plotly_football_pitch/pitch_dimensions.py
plotly_football_pitch/pitch_plot.py
plotly_football_pitch-0.0.3.dist-info/LICENSE.txt
plotly_football_pitch-0.0.3.dist-info/METADATA
plotly_football_pitch-0.0.3.dist-info/WHEEL
plotly_football_pitch-0.0.3.dist-info/top_level.txt
plotly_football_pitch-0.0.3.dist-info/RECORD
