Metadata-Version: 2.1
Name: plotly-football-pitch
Version: 0.0.3
Summary: Package to allow creation of football pitch charts using plotly
Author: Andrew Davies
Maintainer: Andrew Davies
License: This is free and unencumbered software released into the public domain.
Project-URL: Homepage, https://github.com/minimav/plotly-football-pitch
Project-URL: Bug Reports, https://github.com/minimav/plotly-football-pitch/issues
Project-URL: Source, https://github.com/minimav/plotly-football-pitch
Keywords: soccer,football,plotly
Classifier: Development Status :: 3 - Alpha
Classifier: Intended Audience :: Developers
Classifier: License :: OSI Approved :: The Unlicense (Unlicense)
Classifier: Programming Language :: Python :: 3
Classifier: Programming Language :: Python :: 3.8
Classifier: Programming Language :: Python :: 3.9
Classifier: Programming Language :: Python :: 3.10
Classifier: Programming Language :: Python :: 3.11
Classifier: Programming Language :: Python :: 3 :: Only
Requires-Python: >=3.8
License-File: LICENSE.txt
Requires-Dist: plotly
Requires-Dist: plotly-express
Provides-Extra: dev
Requires-Dist: build ; extra == 'dev'
Requires-Dist: jupyter ; extra == 'dev'
Requires-Dist: kaleido ; extra == 'dev'
Requires-Dist: myst-parser ; extra == 'dev'
Requires-Dist: numpy ; extra == 'dev'
Requires-Dist: pre-commit ; extra == 'dev'
Requires-Dist: pytest ; extra == 'dev'
Requires-Dist: sphinx ; extra == 'dev'
Requires-Dist: sphinx-rtd-theme ; extra == 'dev'
